nasa_mcp/__init__.py
nasa_mcp/nasa_api.py
nasa_mcp/server.py
nasa_mcp/test.py
nasa_mcp_server-0.1.20.dist-info/METADATA
nasa_mcp_server-0.1.20.dist-info/WHEEL
nasa_mcp_server-0.1.20.dist-info/entry_points.txt
nasa_mcp_server-0.1.20.dist-info/top_level.txt
nasa_mcp_server-0.1.20.dist-info/RECORD
