Metadata-Version: 2.4
Name: nasa-mcp-server
Version: 0.1.20
Summary: MCP server for NASA Mars Rover images
Author-email: Adithya <adithyasn7@gmail.com>
License: MIT
Project-URL: Homepage, https://github.com/adithya1012/NASA-MCP-Server
Project-URL: Repository, https://github.com/adithya1012/NASA-MCP-Server
Project-URL: Issues, https://github.com/adithya1012/NASA-MCP-Server/issues
Classifier: Development Status :: 3 - Alpha
Classifier: Intended Audience :: Developers
Classifier: License :: OSI Approved :: MIT License
Classifier: Programming Language :: Python :: 3
Classifier: Programming Language :: Python :: 3.8
Classifier: Programming Language :: Python :: 3.9
Classifier: Programming Language :: Python :: 3.10
Classifier: Programming Language :: Python :: 3.11
Requires-Python: >=3.8
Requires-Dist: mcp>=0.1.0
Requires-Dist: httpx>=0.24.0
Requires-Dist: pydantic>=2.0.0
Requires-Dist: requests>=2.25.0
Requires-Dist: Pillow>=8.0.0
Requires-Dist: python-dotenv>=0.19.0
